LICENSE
MANIFEST.in
README.md
requirements.txt
setup.py
analysis/__init__.py
analysis/feature_importance.py
analysis/missing_data.py
analysis/pca.py
analysis/time_series.py
data_report/__init__.py
data_report/init_data_report.py
data_science_analysis_library.egg-info/PKG-INFO
data_science_analysis_library.egg-info/SOURCES.txt
data_science_analysis_library.egg-info/dependency_links.txt
data_science_analysis_library.egg-info/requires.txt
data_science_analysis_library.egg-info/top_level.txt
pre_analysis/__init__.py
pre_analysis/category_proportion.py
pre_analysis/create_correlation_heatmap.py
pre_analysis/distribution.py
pre_analysis/feature_distribution_by_target.py
pre_analysis/outliers.py
pre_analysis/pair_plot.py
pre_analysis/value_count_plot.py
text_analysis/__init__.py
text_analysis/word_cloud.py