Metadata-Version: 2.1
Name: data-science-analysis-library
Version: 1.1
Summary: A Python package for analyzing and visualizing data.
Home-page: https://github.com/Kamil-Krawiec/Data-explorer-library.git
Author: Kamil Krawiec, Maciej Mądry, Maciej Sieroń
Author-email: kamil.krawiec9977@gmail.com
Classifier: Programming Language :: Python :: 3
Classifier: License :: OSI Approved :: MIT License
Classifier: Operating System :: OS Independent
Requires-Python: >=3.9
License-File: LICENSE
